pymccool/__init__.py
pymccool/logging.py
pymccool/math.py
pymccool/tracing.py
pymccool-0.5.6.dist-info/LICENSE
pymccool-0.5.6.dist-info/METADATA
pymccool-0.5.6.dist-info/WHEEL
pymccool-0.5.6.dist-info/top_level.txt
pymccool-0.5.6.dist-info/RECORD
