Metadata-Version: 2.2
Name: pymccool
Version: 0.5.6
Summary: Reusable Python Utilities by McCool
Author-email: Brendon McCool <brendonmccool@gmail.com>
Project-URL: Homepage, https://github.com/bmccool/pyMcCool
Classifier: Programming Language :: Python :: 3
Classifier: License :: OSI Approved :: MIT License
Classifier: Operating System :: OS Independent
Requires-Python: >=3.8
License-File: LICENSE
Requires-Dist: colorlog
Requires-Dist: mock
Requires-Dist: mypy>=1.14.1
Requires-Dist: opentelemetry-exporter-otlp-proto-grpc
Requires-Dist: opentelemetry-exporter-otlp-proto-http
Requires-Dist: python-logging-loki
